g2p_en/__init__.py
g2p_en/checkpoint20.npz
g2p_en/expand/__init__.py
g2p_en/expand/abbreviations.py
g2p_en/expand/number_norm.py
g2p_en/expand/time_norm.py
g2p_en/g2p.py
g2p_en/homographs.en
g2p_arpabet-2.3.0.dist-info/LICENSE
g2p_arpabet-2.3.0.dist-info/METADATA
g2p_arpabet-2.3.0.dist-info/WHEEL
g2p_arpabet-2.3.0.dist-info/RECORD
