Metadata-Version: 2.1
Name: g2p-arpabet
Version: 2.3.0
Summary: A Simple Python Module for English Grapheme To Phoneme Conversion
License: Apache License
Keywords: g2p,g2p_en
Author: Kyubyong Park
Requires-Python: >=3.9,<4.0
Classifier: License :: Other/Proprietary License
Classifier: Programming Language :: Python :: 3
Classifier: Programming Language :: Python :: 3.9
Classifier: Programming Language :: Python :: 3.10
Classifier: Programming Language :: Python :: 3.11
Requires-Dist: distance (>=0.1.3,<0.2.0)
Requires-Dist: inflect (>=0.3.1,<0.4.0)
Requires-Dist: nltk (>=3.2.4,<4.0.0)
Requires-Dist: numpy (>=1.13.1,<2.0.0)
